odoo/addons/account_cutoff_base/README.rst
odoo/addons/account_cutoff_base/__init__.py
odoo/addons/account_cutoff_base/__manifest__.py
odoo/addons/account_cutoff_base/i18n/am.po
odoo/addons/account_cutoff_base/i18n/ar.po
odoo/addons/account_cutoff_base/i18n/de.po
odoo/addons/account_cutoff_base/i18n/el_GR.po
odoo/addons/account_cutoff_base/i18n/es.po
odoo/addons/account_cutoff_base/i18n/es_ES.po
odoo/addons/account_cutoff_base/i18n/es_MX.po
odoo/addons/account_cutoff_base/i18n/fi.po
odoo/addons/account_cutoff_base/i18n/fr.po
odoo/addons/account_cutoff_base/i18n/fr_FR.po
odoo/addons/account_cutoff_base/i18n/hr.po
odoo/addons/account_cutoff_base/i18n/hr_HR.po
odoo/addons/account_cutoff_base/i18n/it.po
odoo/addons/account_cutoff_base/i18n/nb.po
odoo/addons/account_cutoff_base/i18n/nb_NO.po
odoo/addons/account_cutoff_base/i18n/nl.po
odoo/addons/account_cutoff_base/i18n/nl_BE.po
odoo/addons/account_cutoff_base/i18n/nl_NL.po
odoo/addons/account_cutoff_base/i18n/pt_BR.po
odoo/addons/account_cutoff_base/i18n/ro.po
odoo/addons/account_cutoff_base/i18n/sk.po
odoo/addons/account_cutoff_base/i18n/sl.po
odoo/addons/account_cutoff_base/i18n/tr.po
odoo/addons/account_cutoff_base/i18n/zh_CN.po
odoo/addons/account_cutoff_base/models/__init__.py
odoo/addons/account_cutoff_base/models/account_cutoff.py
odoo/addons/account_cutoff_base/models/company.py
odoo/addons/account_cutoff_base/security/account_cutoff_base_security.xml
odoo/addons/account_cutoff_base/security/ir.model.access.csv
odoo/addons/account_cutoff_base/static/description/icon.png
odoo/addons/account_cutoff_base/tests/__init__.py
odoo/addons/account_cutoff_base/tests/test_account_cutoff.py
odoo/addons/account_cutoff_base/views/account_cutoff.xml
odoo/addons/account_cutoff_base/views/company.xml
odoo11_addon_account_cutoff_base-11.0.1.0.0.dist-info/DESCRIPTION.rst
odoo11_addon_account_cutoff_base-11.0.1.0.0.dist-info/METADATA
odoo11_addon_account_cutoff_base-11.0.1.0.0.dist-info/RECORD
odoo11_addon_account_cutoff_base-11.0.1.0.0.dist-info/WHEEL
odoo11_addon_account_cutoff_base-11.0.1.0.0.dist-info/metadata.json
odoo11_addon_account_cutoff_base-11.0.1.0.0.dist-info/top_level.txt
